Workbook

Sheet Suppliers Commodity Code input
B1: Suppliers Input Space | D1: For More details on HS/Commodity Codes Please visit https://www.trade-tariff.service.gov.uk/find_commodity
B2: Automatic Generated
A5: HUSQ Part Number | B5: Description | C5: Commodity Code(10 Digit) | D5: Country of Origin | E5: EU- UK Preference Applies | F5: Automated Generated Short Code | G5: Commodity Code Heading(Based on HMRC) | H5: HMRC (Automatic Description Detect) | I5: Estimated UK import Duty
F6: =LEFT(C6,4) | G6: =VLOOKUP(VALUE(F6),Headings!$A$2:$B$7697,2,) -> #VALUE! | H6: =VLOOKUP(C6,'Full Commodity Code'!$A$2:$B$52437,2,) -> #N/A | I6: =VLOOKUP(C6,'Full Commodity Code'!$A$2:$C$1048576,3,) -> #N/A
F7: =LEFT(C7,4) | G7: =VLOOKUP(VALUE(F7),Headings!$A$2:$B$7697,2,) -> #VALUE! | H7: =VLOOKUP(C7,'Full Commodity Code'!$A$2:$B$52437,2,) -> #N/A | I7: =VLOOKUP(C7,'Full Commodity Code'!$A$2:$C$1048576,3,) -> #N/A
F8: =LEFT(C8,4) | G8: =VLOOKUP(VALUE(F8),Headings!$A$2:$B$7697,2,) -> #VALUE! | H8: =VLOOKUP(C8,'Full Commodity Code'!$A$2:$B$52437,2,) -> #N/A | I8: =VLOOKUP(C8,'Full Commodity Code'!$A$2:$C$1048576,3,) -> #N/A
F9: =LEFT(C9,4) | G9: =VLOOKUP(VALUE(F9),Headings!$A$2:$B$7697,2,) -> #VALUE! | H9: =VLOOKUP(C9,'Full Commodity Code'!$A$2:$B$52437,2,) -> #N/A | I9: =VLOOKUP(C9,'Full Commodity Code'!$A$2:$C$1048576,3,) -> #N/A
F10: =LEFT(C10,4) | G10: =VLOOKUP(VALUE(F10),Headings!$A$2:$B$7697,2,) -> #VALUE! | H10: =VLOOKUP(C10,'Full Commodity Code'!$A$2:$B$52437,2,) -> #N/A | I10: =VLOOKUP(C10,'Full Commodity Code'!$A$2:$C$1048576,3,) -> #N/A
F11: =LEFT(C11,4) | G11: =VLOOKUP(VALUE(F11),Headings!$A$2:$B$7697,2,) -> #VALUE! | H11: =VLOOKUP(C11,'Full Commodity Code'!$A$2:$B$52437,2,) -> #N/A | I11: =VLOOKUP(C11,'Full Commodity Code'!$A$2:$C$1048576,3,) -> #N/A
F12: =LEFT(C12,4) | G12: =VLOOKUP(VALUE(F12),Headings!$A$2:$B$7697,2,) -> #VALUE! | H12: =VLOOKUP(C12,'Full Commodity Code'!$A$2:$B$52437,2,) -> #N/A | I12: =VLOOKUP(C12,'Full Commodity Code'!$A$2:$C$1048576,3,) -> #N/A
F13: =LEFT(C13,4) | G13: =VLOOKUP(VALUE(F13),Headings!$A$2:$B$7697,2,) -> #VALUE! | H13: =VLOOKUP(C13,'Full Commodity Code'!$A$2:$B$52437,2,) -> #N/A | I13: =VLOOKUP(C13,'Full Commodity Code'!$A$2:$C$1048576,3,) -> #N/A
F14: =LEFT(C14,4) | G14: =VLOOKUP(VALUE(F14),Headings!$A$2:$B$7697,2,) -> #VALUE! | H14: =VLOOKUP(C14,'Full Commodity Code'!$A$2:$B$52437,2,) -> #N/A | I14: =VLOOKUP(C14,'Full Commodity Code'!$A$2:$C$1048576,3,) -> #N/A
F15: =LEFT(C15,4) | G15: =VLOOKUP(VALUE(F15),Headings!$A$2:$B$7697,2,) -> #VALUE! | H15: =VLOOKUP(C15,'Full Commodity Code'!$A$2:$B$52437,2,) -> #N/A | I15: =VLOOKUP(C15,'Full Commodity Code'!$A$2:$C$1048576,3,) -> #N/A
F16: =LEFT(C16,4) | G16: =VLOOKUP(VALUE(F16),Headings!$A$2:$B$7697,2,) -> #VALUE! | H16: =VLOOKUP(C16,'Full Commodity Code'!$A$2:$B$52437,2,) -> #N/A | I16: =VLOOKUP(C16,'Full Commodity Code'!$A$2:$C$1048576,3,) -> #N/A
F17: =LEFT(C17,4) | G17: =VLOOKUP(VALUE(F17),Headings!$A$2:$B$7697,2,) -> #VALUE! | H17: =VLOOKUP(C17,'Full Commodity Code'!$A$2:$B$52437,2,) -> #N/A | I17: =VLOOKUP(C17,'Full Commodity Code'!$A$2:$C$1048576,3,) -> #N/A
... F255: =LEFT(C255,4) | G255: =VLOOKUP(VALUE(F255),Headings!$A$2:$B$7697,2,) -> #VALUE! | H255: =VLOOKUP(C255,'Full Commodity Code'!$A$2:$B$52437,2,) -> #N/A | I255: =VLOOKUP(C255,'Full Commodity Code'!$A$2:$C$1048576,3,) -> #N/A

Sheet Full Commodity Code
A1: Commodity code | B1: Description | C1: Third country duty
A2: 101210000 | B2: Pure-bred breeding animals | C2: 0
A3: 101291000 | B3: For slaughter | C3: 0
A4: 101299000 | B4: Other | C4: 0.1
A5: 101300000 | B5: Asses | C5: 0.06
A6: 101900000 | B6: Other | C6: 0.1
A7: 102211000 | B7: Heifers (female bovines that have never calved) | C7: 0
A8: 102213000 | B8: Cows | C8: 0
A9: 102219000 | B9: Other | C9: 0
A10: 102290500 | B10: Of the sub-genus bibos or of the sub-genus poephagus | C10: 0
A11: 102291010 | B11: Young male bovine animals, intended for fattening | C11: 10.00 % + 77.00 GBP / 100 kg
A12: 102291020 | B12: Heifers of the grey, brown or yellow mountain breeds and spotted pinzgau breed, other than for slaughter | C12: 10.00 % + 77.00 GBP / 100 kg
A13: 102291030 | B13: Heifers of the schwyz and fribourg breeds, other than for slaughter | C13: 10.00 % + 77.00 GBP / 100 kg
A14: 102291040 | B14: Heifers of the spotted simmental breed, other than for slaughter | C14: 10.00 % + 77.00 GBP / 100 kg
A15: 102291050 | B15: Bulls of the schwyz, fribourg and spotted simmental breeds, other than for slaughter | C15: 10.00 % + 77.00 GBP / 100 kg
A16: 102291090 | B16: Other | C16: 10.00 % + 77.00 GBP / 100 kg
A17: 102292100 | B17: For slaughter | C17: 10.00 % + 77.00 GBP / 100 kg
A18: 102292910 | B18: Young male bovine animals, intended for fattening | C18: 10.00 % + 77.00 GBP / 100 kg
A19: 102292920 | B19: Heifers of the grey, brown or yellow mountain breeds and spotted pinzgau breed | C19: 10.00 % + 77.00 GBP / 100 kg
A20: 102292930 | B20: Heifers of the schwyz and fribourg breeds | C20: 10.00 % + 77.00 GBP / 100 kg
A21: 102292940 | B21: Heifers of the spotted simmental breed | C21: 10.00 % + 77.00 GBP / 100 kg
A22: 102292950 | B22: Bulls of the schwyz, fribourg and spotted simmental breeds | C22: 10.00 % + 77.00 GBP / 100 kg
... A51: 102299999 | B51: Other | C51: 10.00 % + 77.00 GBP / 100 kg
A52: 102310000 | B52: Pure-bred breeding animals | C52: 0
A53: 102391010 | B53: Of a weight exceeding 160 kg | C53: 10.00 % + 77.00 GBP / 100 kg
A54: 102391090 | B54: Other | C54: 10.00 % + 77.00 GBP / 100 kg
A55: 102399000 | B55: Other | C55: 0
A56: 102902000 | B56: Pure-bred breeding animals | C56: 0
A57: 102909110 | B57: Of a weight exceeding 160 kg | C57: 10.00 % + 77.00 GBP / 100 kg
A58: 102909190 | B58: Other | C58: 10.00 % + 77.00 GBP / 100 kg
A59: 102909900 | B59: Other | C59: 0
A60: 103100000 | B60: Pure-bred breeding animals | C60: 0
A61: 103911000 | B61: Domestic species | C61: 34.00 GBP / 100 kg
A62: 103919000 | B62: Other | C62: 0
A63: 103921100 | B63: Sows having farrowed at least once, of a weight of not less than 160 kg | C63: 29.00 GBP / 100 kg
A64: 103921900 | B64: Other | C64: 34.00 GBP / 100 kg
A65: 103929000 | B65: Other | C65: 0
A66: 104101000 | B66: Pure-bred breeding animals | C66: 0
A67: 104103000 | B67: Lambs (up to a year old) | C67: 67.00 GBP / 100 kg
A68: 104108000 | B68: Other | C68: 67.00 GBP / 100 kg
A69: 104201000 | B69: Pure-bred breeding animals | C69: 0.02
A70: 104209000 | B70: Other | C70: 67.00 GBP / 100 kg
A71: 105111100 | B71: Laying stocks | C71: 43.00 GBP / 1000 p/st
A72: 105111900 | B72: Other | C72: 43.00 GBP / 1000 p/st
A73: 105119100 | B73: Laying stocks | C73: 43.00 GBP / 1000 p/st
A74: 105119900 | B74: Other | C74: 43.00 GBP / 1000 p/st
A75: 105120000 | B75: Turkeys | C75: 127.00 GBP / 1000 p/st
A76: 105130000 | B76: Ducks | C76: 43.00 GBP / 1000 p/st
A77: 105140000 | B77: Geese | C77: 127.00 GBP / 1000 p/st
A78: 105150000 | B78: Guinea fowls | C78: 43.00 GBP / 1000 p/st
A79: 105940000 | B79: Fowls of the species gallus domesticus | C79: 17.00 GBP / 100 kg
A80: 105991000 | B80: Ducks | C80: 27.00 GBP / 100 kg
A81: 105992000 | B81: Geese | C81: 26.00 GBP / 100 kg
... A83: 105995000 | B83: Guinea fowls | C83: 28.00 GBP / 100 kg
A84: 106110000 | B84: Primates | C84: 0
A85: 106120000 | B85: Whales, dolphins and porpoises (mammals of the order cetacea); manatees and dugongs (mammals of the order sirenia); seals, sea lions and walruses (mammals of the suborder pinnipedia) | C85: 0
A86: 106130000 | B86: Camels and other camelids (camelidae) | C86: 0
A87: 106141000 | B87: Domestic rabbits | C87: 0.02
A88: 106149000 | B88: Other | C88: 0
A89: 106190000 | B89: Other | C89: 0
A90: 106200000 | B90: Reptiles (including snakes and turtles) | C90: 0
A91: 106310000 | B91: Birds of prey | C91: 0
A92: 106320000 | B92: Psittaciformes (including parrots, parakeets, macaws and cockatoos) | C92: 0
A93: 106330000 | B93: Ostriches; emus (dromaius novaehollandiae) | C93: 0
A94: 106391000 | B94: Pigeons | C94: 0.06
A95: 106398000 | B95: Other | C95: 0
... A100: 106900090 | B100: Other | C100: 0
A101: 201100021 | B101: Of bison | C101: 12.00 % + 147.00 GBP / 100 kg
A102: 201100029 | B102: Other | C102: 12.00 % + 147.00 GBP / 100 kg
A103: 201100092 | B103: Of bison | C103: 12.00 % + 147.00 GBP / 100 kg
A104: 201100094 | B104: Other | C104: 12.00 % + 147.00 GBP / 100 kg
A105: 201100097 | B105: Of bison | C105: 12.00 % + 147.00 GBP / 100 kg
A106: 201100098 | B106: Other | C106: 12.00 % + 147.00 GBP / 100 kg
A107: 201202021 | B107: Of bison | C107: 12.00 % + 147.00 GBP / 100 kg
A108: 201202029 | B108: Other | C108: 12.00 % + 147.00 GBP / 100 kg
A109: 201202092 | B109: Of bison | C109: 12.00 % + 147.00 GBP / 100 kg
A110: 201202094 | B110: Other | C110: 12.00 % + 147.00 GBP / 100 kg
A111: 201202097 | B111: Of bison | C111: 12.00 % + 147.00 GBP / 100 kg
A112: 201202098 | B112: Other | C112: 12.00 % + 147.00 GBP / 100 kg
... A194: 203111000 | B194: Of domestic swine | C194: 44.00 GBP / 100 kg
A195: 203119000 | B195: Other | C195: 0
A196: 203121100 | B196: Hams and cuts thereof | C196: 65.00 GBP / 100 kg
A197: 203121900 | B197: Shoulders and cuts thereof | C197: 50.00 GBP / 100 kg
A198: 203129000 | B198: Other | C198: 0
A199: 203191100 | B199: Fore-ends and cuts thereof | C199: 50.00 GBP / 100 kg
A200: 203191300 | B200: Loins and cuts thereof, with bone in | C200: 72.00 GBP / 100 kg
A201: 203191500 | B201: Bellies (streaky) and cuts thereof | C201: 39.00 GBP / 100 kg
A202: 203195510 | B202: Tenderloin, presented separately | C202: 72.00 GBP / 100 kg
A203: 203195515 | B203: Loins | C203: 72.00 GBP / 100 kg
A204: 203195525 | B204: Cuts | C204: 72.00 GBP / 100 kg
A205: 203195530 | B205: Ham and cuts of ham | C205: 72.00 GBP / 100 kg
A206: 203195590 | B206: Other | C206: 72.00 GBP / 100 kg
A207: 203195900 | B207: Other | C207: 72.00 GBP / 100 kg
A208: 203199000 | B208: Other | C208: 0
A209: 203211000 | B209: Of domestic swine | C209: 44.00 GBP / 100 kg
A210: 203219000 | B210: Other | C210: 0
A211: 203221100 | B211: Hams and cuts thereof | C211: 65.00 GBP / 100 kg
A212: 203221900 | B212: Shoulders and cuts thereof | C212: 50.00 GBP / 100 kg
A213: 203229000 | B213: Other | C213: 0
A214: 203291100 | B214: Fore-ends and cuts thereof | C214: 50.00 GBP / 100 kg
...

Sheet Headings
A1: Number | B1: Detail
A2: 5305 | B2: Abaca (Manilla Hemp)
A3: 9503 | B3: Abaci
A4: 9018 | B4: Abcess needles, dental
A5: 3806 | B5: Abietic acid
A6: 6805 | B6: Abrasives on a base of paper or fabrics
A7: 2513 | B7: Abrasives, natural
A8: 3301 | B8: Absolutes (essential oils)
A9: 8418 | B9: Absorbers
A10: 9027 | B10: Absorptiometers
A11: 7020 | B11: Absorption drums, of glass
A12: 8543 | B12: Accelerators - particle
A13: 9022 | B13: Accelerators - particle
... A924: 9001 | B924: Cable - Optical fibre
A925: 8544 | B925: Cable - Submarine telecommunications, insulated | O925: Yes
A926: 8544 | B926: Cable - Telecommunications, insulated | O926: No
A927: 7614 | B927: Cable - Wire, not electrically insulated, aluminium
A928: 7413 | B928: Cable - Wire, not electrically insulated, copper
A929: 8543 | B929: Cable TV equipment - Amplifier
A930: 8527 | B930: Cable TV equipment - Audio receiver/decoders
A931: 8528 | B931: Cable TV equipment - Integrated receiver/decoder
A932: 8543 | B932: Cable TV equipment - Line extender
A933: 8517 | B933: Cable TV equipment - Optoelectronic receiver
A934: 8517 | B934: Cable TV equipment - Optoelectronic transmitter
A935: 7312 | B935: Cables, iron or steel
A936: 5607 | B936: Cables, textile
A937: 6310 | B937: Cables, textile, scrap or worn out
A938: 8426 | B938: Cableways
... A7697: 106 | B7697: Zoo animals
